{
  "brokerageId": "393897513",
  "numContracts": 1,
  "position": 110,
  "sellingIntervals": [
    {
      "active": true,
      "crossed": true,
      "orderSide": "SELL",
      "price": 12.4
    },
    {
      "active": true,
      "crossed": true,
      "orderSide": "SELL",
      "price": 12.3
    },
    {
      "active": true,
      "crossed": true,
      "orderSide": "SELL",
      "price": 12.2
    },
    {
      "active": true,
      "crossed": true,
      "orderSide": "SELL",
      "price": 12.1
    },
    {
      "active": true,
      "crossed": true,
      "orderSide": "SELL",
      "price": 12
    },
    {
      "active": true,
      "crossed": true,
      "orderSide": "SELL",
      "price": 11.9
    },
    {
      "active": true,
      "crossed": true,
      "orderSide": "SELL",
      "price": 11.8
    },
    {
      "active": true,
      "crossed": true,
      "orderSide": "SELL",
      "price": 11.7
    },
    {
      "active": true,
      "crossed": true,
      "orderSide": "SELL",
      "price": 11.6
    },
    {
      "active": true,
      "crossed": true,
      "orderSide": "SELL",
      "price": 11.5
    },
    {
      "active": true,
      "crossed": true,
      "orderSide": "SELL",
      "price": 11.4
    }
  ],
  "buyingIntervals": [
    {
      "active": false,
      "crossed": false,
      "orderSide": "BUY",
      "price": 12.35
    },
    {
      "active": false,
      "crossed": false,
      "orderSide": "BUY",
      "price": 12.25
    },
    {
      "active": false,
      "crossed": false,
      "orderSide": "BUY",
      "price": 12.15
    },
    {
      "active": false,
      "crossed": false,
      "orderSide": "BUY",
      "price": 12.05
    },
    {
      "active": false,
      "crossed": false,
      "orderSide": "BUY",
      "price": 11.95
    },
    {
      "active": false,
      "crossed": false,
      "orderSide": "BUY",
      "price": 11.85
    },
    {
      "active": false,
      "crossed": false,
      "orderSide": "BUY",
      "price": 11.75
    },
    {
      "active": false,
      "crossed": false,
      "orderSide": "BUY",
      "price": 11.65
    },
    {
      "active": false,
      "crossed": false,
      "orderSide": "BUY",
      "price": 11.55
    },
    {
      "active": false,
      "crossed": false,
      "orderSide": "BUY",
      "price": 11.45
    },
    {
      "active": false,
      "crossed": false,
      "orderSide": "BUY",
      "price": 11.35
    }
  ]
}
