{
  "brokerageId": "554208351",
  "brokerageTradingCostPerShare": 0.005,
  "targetPosition": 102,
  "sharesPerInterval": 34,
  "spaceBetweenIntervals": 0.05,
  "intervalProfit": 0.01,
  "numContracts": 1,
  "premiumSold": 0.32,
  "callStrikePrice": 13,
  "initialPrice": 11.45,
  "putStrikePrice": 10,
  "position": 0,
  "lastSignificantPrice": 11.45,
  "transitoryValue": 32,
  "unrealizedValue": 32,
  "intervals": [
    {
      "type": "LONG",
      "positionLimit": 102,
      "SELL": {
        "price": 11.61,
        "active": false,
        "crossed": false
      },
      "BUY": {
        "price": 11.6,
        "active": true,
        "crossed": true
      }
    },
    {
      "type": "LONG",
      "positionLimit": 68,
      "SELL": {
        "price": 11.56,
        "active": false,
        "crossed": false
      },
      "BUY": {
        "price": 11.55,
        "active": true,
        "crossed": true
      }
    },
    {
      "type": "LONG",
      "positionLimit": 34,
      "SELL": {
        "price": 11.51,
        "active": false,
        "crossed": false
      },
      "BUY": {
        "price": 11.5,
        "active": true,
        "crossed": true
      }
    },
    {
      "type": "LONG",
      "positionLimit": 0,
      "SELL": {
        "price": 11.46,
        "active": false,
        "crossed": false
      },
      "BUY": {
        "price": 11.45,
        "active": true,
        "crossed": true
      }
    },
    {
      "type": "SHORT",
      "positionLimit": 0,
      "SELL": {
        "price": 11.41,
        "active": true,
        "crossed": true
      },
      "BUY": {
        "price": 11.4,
        "active": false,
        "crossed": false
      }
    },
    {
      "type": "SHORT",
      "positionLimit": -34,
      "SELL": {
        "price": 11.36,
        "active": true,
        "crossed": true
      },
      "BUY": {
        "price": 11.35,
        "active": false,
        "crossed": false
      }
    },
    {
      "type": "SHORT",
      "positionLimit": -68,
      "SELL": {
        "price": 11.31,
        "active": true,
        "crossed": true
      },
      "BUY": {
        "price": 11.3,
        "active": false,
        "crossed": false
      }
    },
    {
      "type": "SHORT",
      "positionLimit": -102,
      "SELL": {
        "price": 11.26,
        "active": true,
        "crossed": true
      },
      "BUY": {
        "price": 11.25,
        "active": false,
        "crossed": false
      }
    }
  ],
  "tradingLogs": []
}
